xphasesync/__init__.py
xphasesync/xphasesync.py
xphasesync-0.1.0.dist-info/licenses/LICENSE
xphasesync-0.1.0.dist-info/METADATA
xphasesync-0.1.0.dist-info/WHEEL
xphasesync-0.1.0.dist-info/top_level.txt
xphasesync-0.1.0.dist-info/RECORD
