Metadata-Version: 2.4
Name: xphasesync
Version: 0.1.0
Summary: "Phase synchronization analysis of two time series using Numpy and Xarray."
Home-page: https://github.com/senclimate/xphasesync
Author: Sen Zhao
Author-email: zhaos@hawaii.edu
License: MIT
Classifier: Programming Language :: Python :: 3
Classifier: License :: OSI Approved :: MIT License
Classifier: Operating System :: OS Independent
Classifier: Intended Audience :: Science/Research
Classifier: Topic :: Scientific/Engineering
Requires-Python: >=3.8
License-File: LICENSE
Requires-Dist: numpy
Requires-Dist: xarray
Requires-Dist: scipy
Dynamic: license-file
